yalexs_ble/__init__.py
yalexs_ble/const.py
yalexs_ble/lock.py
yalexs_ble/push.py
yalexs_ble/py.typed
yalexs_ble/secure_session.py
yalexs_ble/session.py
yalexs_ble/util.py
yalexs_ble-3.2.6.dist-info/METADATA
yalexs_ble-3.2.6.dist-info/WHEEL
yalexs_ble-3.2.6.dist-info/licenses/LICENSE
yalexs_ble-3.2.6.dist-info/RECORD
