Metadata-Version: 2.4
Name: yalexs-ble
Version: 3.2.6
Summary: Bluetooth control of Yale and August locks
License-Expression: GPL-3.0-only
License-File: LICENSE
Author: J. Nick Koston
Author-email: nick@koston.org
Requires-Python: >=3.11
Classifier: Development Status :: 2 - Pre-Alpha
Classifier: Intended Audience :: Developers
Classifier: Natural Language :: English
Classifier: Operating System :: OS Independent
Classifier: Programming Language :: Python :: 3
Classifier: Programming Language :: Python :: 3.11
Classifier: Programming Language :: Python :: 3.12
Classifier: Programming Language :: Python :: 3.13
Classifier: Programming Language :: Python :: 3.14
Classifier: Topic :: Software Development :: Libraries
Requires-Dist: async-interrupt (>=1.1.1)
Requires-Dist: async-timeout (>=3.0.0) ; python_version < "3.11"
Requires-Dist: bleak (>=0.19.0)
Requires-Dist: bleak-retry-connector (>=3.4.0)
Requires-Dist: cryptography (>=38.0.0)
Requires-Dist: lru-dict (>=1.1.4)
Project-URL: Bug Tracker, https://github.com/bdraco/yalexs-ble/issues
Project-URL: Changelog, https://github.com/bdraco/yalexs-ble/blob/main/CHANGELOG.md
Project-URL: Documentation, https://yalexs-ble.readthedocs.io
Project-URL: Repository, https://github.com/bdraco/yalexs-ble
